sendpy/__init__.py
sendpy/__main__.py
sendpy/configuration.py
sendpy/send.py
sendpy/usage.py
sendpy-1.0.2.data/scripts/sendpy
sendpy-1.0.2.dist-info/LICENSE
sendpy-1.0.2.dist-info/METADATA
sendpy-1.0.2.dist-info/WHEEL
sendpy-1.0.2.dist-info/entry_points.txt
sendpy-1.0.2.dist-info/top_level.txt
sendpy-1.0.2.dist-info/RECORD
