Metadata-Version: 2.1
Name: sendpy
Version: 1.0.2
Summary: Email and text notification program
Home-page: https://github.com/tdulcet/Send-Msg-CLI
Author: Daniel Connelly and Teal Dulcet
Author-email: connellyd2050@gmail.com
License: GPL
Project-URL: Bug Reports, https://github.com/tdulcet/Send-Msg-CLI
Project-URL: Funding, https://www.paypal.com/cgi-bin/webscr?cmd=_s-xclick&hosted_button_id=NJ4PULABRVNCC
Project-URL: Source, https://github.com/tdulcet/Send-Msg-CLI
Keywords: sendpy email e-mail send text notification g-mail
Classifier: Programming Language :: Python :: 3.6
Classifier: Programming Language :: Python :: 3.7
Classifier: Programming Language :: Python :: 3.8
Classifier: Programming Language :: Python :: 3.9
Classifier: Programming Language :: Python :: 3.10
Classifier: Programming Language :: Python :: 3.11
Classifier: Programming Language :: Python :: 3.12
Classifier: License :: OSI Approved :: GNU General Public License (GPL)
Classifier: Operating System :: OS Independent
Requires-Python: >=3.6
License-File: LICENSE
